fastapi_users_tortoise/__init__.py
fastapi_users_tortoise/access_token.py
fastapi_users_tortoise/py.typed
fastapi_users_tortoise-0.2.0.dist-info/LICENSE
fastapi_users_tortoise-0.2.0.dist-info/WHEEL
fastapi_users_tortoise-0.2.0.dist-info/METADATA
fastapi_users_tortoise-0.2.0.dist-info/RECORD
